semantic_mcp/__init__.py
semantic_mcp/log.py
semantic_mcp/main.py
semantic_mcp/mcp_server.py
semantic_mcp/models.py
semantic_mcp/runtime_engine.py
semantic_mcp/services/__init__.py
semantic_mcp/services/content_manager.py
semantic_mcp/services/discovery_client.py
semantic_mcp/settings.py
semantic_mcp/tools/__init__.py
semantic_mcp/tools/cancel_task.py
semantic_mcp/tools/execute_tool.py
semantic_mcp/tools/get_content.py
semantic_mcp/tools/get_server_info.py
semantic_mcp/tools/get_server_tools.py
semantic_mcp/tools/get_statistics.py
semantic_mcp/tools/get_tool_details.py
semantic_mcp/tools/list_running.py
semantic_mcp/tools/list_servers.py
semantic_mcp/tools/list_tasks.py
semantic_mcp/tools/manage_server.py
semantic_mcp/tools/poll_task.py
semantic_mcp/tools/search_servers.py
semantic_mcp/tools/search_tools.py
semantic_mcp-0.2.1.dist-info/WHEEL
semantic_mcp-0.2.1.dist-info/entry_points.txt
semantic_mcp-0.2.1.dist-info/METADATA
semantic_mcp-0.2.1.dist-info/RECORD
