Metadata-Version: 2.3
Name: semantic-mcp
Version: 0.2.1
Summary: Semantic router for MCP ecosystems - Discover, manage, and execute tools across multiple MCP servers with progressive disclosure
Keywords: mcp,model-context-protocol,semantic-search,llm,ai-agents,tool-routing,semantic-mcp
Author: BA Ibrahima
Author-email: BA Ibrahima <ibrahima.elmokhtar@gmail.com>
License: MIT
Classifier: Development Status :: 4 - Beta
Classifier: Intended Audience :: Developers
Classifier: License :: OSI Approved :: MIT License
Classifier: Programming Language :: Python :: 3
Classifier: Programming Language :: Python :: 3.12
Classifier: Topic :: Software Development :: Libraries :: Python Modules
Requires-Dist: fastmcp>=2.0.0
Requires-Dist: mcp>=1.3.0
Requires-Dist: pyzmq>=26.0.0
Requires-Dist: httpx>=0.27.0
Requires-Dist: pydantic-settings>=2.6.0
Requires-Dist: tiktoken>=0.8.0
Requires-Dist: openai>=1.57.0
Requires-Dist: python-dotenv>=1.0.0
Requires-Dist: click>=8.1.0
Requires-Python: >=3.12
Project-URL: Homepage, https://github.com/milkymap/semantic-mcp
Project-URL: Issues, https://github.com/milkymap/semantic-mcp/issues
Project-URL: Repository, https://github.com/milkymap/semantic-mcp
